<annotation>
  <folder>VOC2012</folder>
  <filename>1187.jpg</filename>
  <path>E:\981021_VR1\R_CNN\VOCdevkit\VOC2012\JPEGImages\1187.jpg</path>
  <source>
    <database>Unknown</database>
  </source>
  <size>
    <width>640</width>
    <height>128</height>
    <depth>3</depth>
  </size>
  <segmented>0</segmented>
  <object>
    <name>5</name>
    <pose>Unspecified</pose>
    <truncated>0</truncated>
    <difficult>0</difficult>
    <bndbox>
      <xmin>41</xmin>
      <ymin>22</ymin>
      <xmax>103</xmax>
      <ymax>120</ymax>
    </bndbox>
  </object>
  <object>
    <name>1</name>
    <pose>Unspecified</pose>
    <truncated>0</truncated>
    <difficult>0</difficult>
    <bndbox>
      <xmin>115</xmin>
      <ymin>19</ymin>
      <xmax>158</xmax>
      <ymax>114</ymax>
    </bndbox>
  </object>
  <object>
    <name>saat</name>
    <pose>Unspecified</pose>
    <truncated>0</truncated>
    <difficult>0</difficult>
    <bndbox>
      <xmin>170</xmin>
      <ymin>27</ymin>
      <xmax>285</xmax>
      <ymax>102</ymax>
    </bndbox>
  </object>
  <object>
    <name>3</name>
    <pose>Unspecified</pose>
    <truncated>0</truncated>
    <difficult>0</difficult>
    <bndbox>
      <xmin>294</xmin>
      <ymin>4</ymin>
      <xmax>351</xmax>
      <ymax>104</ymax>
    </bndbox>
  </object>
  <object>
    <name>6</name>
    <pose>Unspecified</pose>
    <truncated>0</truncated>
    <difficult>0</difficult>
    <bndbox>
      <xmin>358</xmin>
      <ymin>4</ymin>
      <xmax>414</xmax>
      <ymax>102</ymax>
    </bndbox>
  </object>
  <object>
    <name>9</name>
    <pose>Unspecified</pose>
    <truncated>0</truncated>
    <difficult>0</difficult>
    <bndbox>
      <xmin>424</xmin>
      <ymin>2</ymin>
      <xmax>479</xmax>
      <ymax>94</ymax>
    </bndbox>
  </object>
  <object>
    <name>5</name>
    <pose>Unspecified</pose>
    <truncated>0</truncated>
    <difficult>0</difficult>
    <bndbox>
      <xmin>503</xmin>
      <ymin>11</ymin>
      <xmax>560</xmax>
      <ymax>97</ymax>
    </bndbox>
  </object>
  <object>
    <name>4</name>
    <pose>Unspecified</pose>
    <truncated>0</truncated>
    <difficult>0</difficult>
    <bndbox>
      <xmin>567</xmin>
      <ymin>8</ymin>
      <xmax>623</xmax>
      <ymax>92</ymax>
    </bndbox>
  </object>
</annotation>
