<annotation>
  <folder>VOC2012</folder>
  <filename>594.jpg</filename>
  <path>E:\981021_VR1\R_CNN\VOCdevkit\VOC2012\JPEGImages\594.jpg</path>
  <source>
    <database>Unknown</database>
  </source>
  <size>
    <width>640</width>
    <height>128</height>
    <depth>3</depth>
  </size>
  <segmented>0</segmented>
  <object>
    <name>4</name>
    <pose>Unspecified</pose>
    <truncated>0</truncated>
    <difficult>0</difficult>
    <bndbox>
      <xmin>4</xmin>
      <ymin>28</ymin>
      <xmax>60</xmax>
      <ymax>87</ymax>
    </bndbox>
  </object>
  <object>
    <name>6</name>
    <pose>Unspecified</pose>
    <truncated>0</truncated>
    <difficult>0</difficult>
    <bndbox>
      <xmin>66</xmin>
      <ymin>29</ymin>
      <xmax>137</xmax>
      <ymax>87</ymax>
    </bndbox>
  </object>
  <object>
    <name>be</name>
    <pose>Unspecified</pose>
    <truncated>0</truncated>
    <difficult>0</difficult>
    <bndbox>
      <xmin>149</xmin>
      <ymin>39</ymin>
      <xmax>265</xmax>
      <ymax>92</ymax>
    </bndbox>
  </object>
  <object>
    <name>4</name>
    <pose>Unspecified</pose>
    <truncated>0</truncated>
    <difficult>0</difficult>
    <bndbox>
      <xmin>282</xmin>
      <ymin>34</ymin>
      <xmax>345</xmax>
      <ymax>93</ymax>
    </bndbox>
  </object>
  <object>
    <name>9</name>
    <pose>Unspecified</pose>
    <truncated>0</truncated>
    <difficult>0</difficult>
    <bndbox>
      <xmin>352</xmin>
      <ymin>35</ymin>
      <xmax>410</xmax>
      <ymax>94</ymax>
    </bndbox>
  </object>
  <object>
    <name>5</name>
    <pose>Unspecified</pose>
    <truncated>0</truncated>
    <difficult>0</difficult>
    <bndbox>
      <xmin>417</xmin>
      <ymin>36</ymin>
      <xmax>487</xmax>
      <ymax>93</ymax>
    </bndbox>
  </object>
  <object>
    <name>6</name>
    <pose>Unspecified</pose>
    <truncated>0</truncated>
    <difficult>0</difficult>
    <bndbox>
      <xmin>506</xmin>
      <ymin>45</ymin>
      <xmax>569</xmax>
      <ymax>98</ymax>
    </bndbox>
  </object>
  <object>
    <name>6</name>
    <pose>Unspecified</pose>
    <truncated>0</truncated>
    <difficult>0</difficult>
    <bndbox>
      <xmin>577</xmin>
      <ymin>45</ymin>
      <xmax>634</xmax>
      <ymax>101</ymax>
    </bndbox>
  </object>
</annotation>
