<annotation>
  <folder>VOC2012</folder>
  <filename>673.jpg</filename>
  <path>E:\981021_VR1\R_CNN\VOCdevkit\VOC2012\JPEGImages\673.jpg</path>
  <source>
    <database>Unknown</database>
  </source>
  <size>
    <width>640</width>
    <height>128</height>
    <depth>3</depth>
  </size>
  <segmented>0</segmented>
  <object>
    <name>8</name>
    <pose>Unspecified</pose>
    <truncated>0</truncated>
    <difficult>0</difficult>
    <bndbox>
      <xmin>47</xmin>
      <ymin>4</ymin>
      <xmax>86</xmax>
      <ymax>64</ymax>
    </bndbox>
  </object>
  <object>
    <name>8</name>
    <pose>Unspecified</pose>
    <truncated>0</truncated>
    <difficult>0</difficult>
    <bndbox>
      <xmin>95</xmin>
      <ymin>10</ymin>
      <xmax>145</xmax>
      <ymax>69</ymax>
    </bndbox>
  </object>
  <object>
    <name>taa</name>
    <pose>Unspecified</pose>
    <truncated>0</truncated>
    <difficult>0</difficult>
    <bndbox>
      <xmin>164</xmin>
      <ymin>22</ymin>
      <xmax>238</xmax>
      <ymax>84</ymax>
    </bndbox>
  </object>
  <object>
    <name>9</name>
    <pose>Unspecified</pose>
    <truncated>0</truncated>
    <difficult>0</difficult>
    <bndbox>
      <xmin>261</xmin>
      <ymin>33</ymin>
      <xmax>313</xmax>
      <ymax>95</ymax>
    </bndbox>
  </object>
  <object>
    <name>7</name>
    <pose>Unspecified</pose>
    <truncated>0</truncated>
    <difficult>0</difficult>
    <bndbox>
      <xmin>323</xmin>
      <ymin>38</ymin>
      <xmax>384</xmax>
      <ymax>101</ymax>
    </bndbox>
  </object>
  <object>
    <name>6</name>
    <pose>Unspecified</pose>
    <truncated>0</truncated>
    <difficult>0</difficult>
    <bndbox>
      <xmin>387</xmin>
      <ymin>43</ymin>
      <xmax>450</xmax>
      <ymax>106</ymax>
    </bndbox>
  </object>
  <object>
    <name>7</name>
    <pose>Unspecified</pose>
    <truncated>0</truncated>
    <difficult>0</difficult>
    <bndbox>
      <xmin>473</xmin>
      <ymin>64</ymin>
      <xmax>529</xmax>
      <ymax>124</ymax>
    </bndbox>
  </object>
  <object>
    <name>7</name>
    <pose>Unspecified</pose>
    <truncated>0</truncated>
    <difficult>0</difficult>
    <bndbox>
      <xmin>539</xmin>
      <ymin>71</ymin>
      <xmax>604</xmax>
      <ymax>127</ymax>
    </bndbox>
  </object>
</annotation>
